README.txt
setup.py
tstamp/__init__.py
tstamp/tstamp.py
tstamp.egg-info/PKG-INFO
tstamp.egg-info/SOURCES.txt
tstamp.egg-info/dependency_links.txt
tstamp.egg-info/top_level.txt