Metadata-Version: 1.0
Name: tstamp
Version: 1.0.2
Summary: A library which provides a higher level interface for creating and formatting timestamps.
Home-page: https://github.com/iLoveTux/timestamp
Author: iLoveTux
Author-email: ilovetux@ymail.com
License: MIT
Keywords: time timestamp epoch
Platform: UNKNOWN
